[{"line":2,"elements":[{"start_timestamp":"2023-04-10T18:42:17.757Z","line":3,"name":"TC02_search for tesla","description":"","id":"assertions2;tc02-search-for-tesla","type":"scenario","keyword":"Scenario","steps":[{"result":{"duration":4826204700,"status":"passed"},"line":4,"name":"I navigate to \"https://google.com\"","match":{"arguments":[{"val":"\"https://google.com\"","offset":14}],"location":"stepdefinitions.GoogleStepDefinitions.ı_navigate_to(java.lang.String)"},"keyword":"Given "},{"result":{"duration":2863667100,"status":"passed"},"line":5,"name":"I search for \"Tesla\"","match":{"arguments":[{"val":"\"Tesla\"","offset":13}],"location":"stepdefinitions.GoogleStepDefinitions.ı_search_for(java.lang.String)"},"keyword":"When "},{"result":{"duration":143998200,"status":"passed"},"line":6,"name":"verify page source contains \"Tesla\"","match":{"arguments":[{"val":"\"Tesla\"","offset":28}],"location":"stepdefinitions.GoogleStepDefinitions.verify_page_source_contains(java.lang.String)"},"keyword":"Then "},{"result":{"duration":166003500,"status":"passed"},"line":7,"name":"verify the result should contain \"bulundu\" keyword","match":{"arguments":[{"val":"\"bulundu\"","offset":33}],"location":"stepdefinitions.GoogleStepDefinitions.verify_the_result_should_contain_keyword(java.lang.String)"},"keyword":"Then "},{"result":{"duration":70997900,"status":"passed"},"line":8,"name":"the first result in the page sections should contain \"Tesla\"","match":{"arguments":[{"val":"\"Tesla\"","offset":53}],"location":"stepdefinitions.GoogleStepDefinitions.the_first_result_in_the_page_sections_should_contain(java.lang.String)"},"keyword":"Then "}],"tags":[{"name":"@assertions2"}]}],"name":"assertions2","description":"","id":"assertions2","keyword":"Feature","uri":"file:src/test/resources/04_assertions2.feature","tags":[{"name":"@assertions2","type":"Tag","location":{"line":1,"column":1}}]}]